matrixplot.py
matrixplot-0.5.dist-info/METADATA
matrixplot-0.5.dist-info/WHEEL
matrixplot-0.5.dist-info/top_level.txt
matrixplot-0.5.dist-info/RECORD
