Metadata-Version: 2.2
Name: matrixplot
Version: 0.5
Summary: 📊 Conveniently plot matrices in matplotlib
Classifier: License :: OSI Approved :: MIT License
Requires-Dist: matplotlib
Dynamic: classifier
Dynamic: description
Dynamic: description-content-type
Dynamic: requires-dist
Dynamic: summary
